[{"name": "dds75-lb-001.parquet", "size": 6124, "mtime": 1758217010, "type": "Parquet"}, {"name": "dds75-lb-001_raw.ndjson", "size": 181488, "mtime": 1758217010, "type": "NDJSON"}, {"name": "dds75-lb-02.parquet", "size": 6338, "mtime": 1758217011, "type": "Parquet"}, {"name": "dds75-lb-02_raw.ndjson", "size": 158947, "mtime": 1758217011, "type": "NDJSON"}, {"name": "dds75-lb-03.parquet", "size": 6174, "mtime": 1758217012, "type": "Parquet"}, {"name": "dds75-lb-03_raw.ndjson", "size": 155605, "mtime": 1758217012, "type": "NDJSON"}, {"name": "dds75-lb-04.parquet", "size": 6260, "mtime": 1758217013, "type": "Parquet"}, {"name": "dds75-lb-04_raw.ndjson", "size": 196171, "mtime": 1758217013, "type": "NDJSON"}, {"name": "dds75-lb-05.parquet", "size": 6273, "mtime": 1758217013, "type": "Parquet"}, {"name": "dds75-lb-05_raw.ndjson", "size": 167346, "mtime": 1758217013, "type": "NDJSON"}, {"name": "dds75-lb-06.parquet", "size": 6119, "mtime": 1758217015, "type": "Parquet"}, {"name": "dds75-lb-06_raw.ndjson", "size": 165320, "mtime": 1758217015, "type": "NDJSON"}, {"name": "dds75-lb-07.parquet", "size": 6217, "mtime": 1758217015, "type": "Parquet"}, {"name": "dds75-lb-07_raw.ndjson", "size": 161925, "mtime": 1758217015, "type": "NDJSON"}, {"name": "dds75-lb-08.parquet", "size": 6367, "mtime": 1758217016, "type": "Parquet"}, {"name": "dds75-lb-08_raw.ndjson", "size": 183673, "mtime": 1758217016, "type": "NDJSON"}, {"name": "dds75-lb-09.parquet", "size": 6288, "mtime": 1758217017, "type": "Parquet"}, {"name": "dds75-lb-09_raw.ndjson", "size": 174757, "mtime": 1758217017, "type": "NDJSON"}, {"name": "dds75-lb-10.parquet", "size": 6232, "mtime": 1758217018, "type": "Parquet"}, {"name": "dds75-lb-10_raw.ndjson", "size": 184723, "mtime": 1758217018, "type": "NDJSON"}, {"name": "dds75-lb-11.parquet", "size": 6265, "mtime": 1758217019, "type": "Parquet"}, {"name": "dds75-lb-11_raw.ndjson", "size": 163581, "mtime": 1758217019, "type": "NDJSON"}, {"name": "dds75-lb-12.parquet", "size": 6229, "mtime": 1758217023, "type": "Parquet"}, {"name": "dds75-lb-12_raw.ndjson", "size": 156350, "mtime": 1758217023, "type": "NDJSON"}, {"name": "dds75-lb-13.parquet", "size": 6264, "mtime": 1758217029, "type": "Parquet"}, {"name": "dds75-lb-13_raw.ndjson", "size": 172046, "mtime": 1758217029, "type": "NDJSON"}, {"name": "dds75-lb-14.parquet", "size": 6351, "mtime": 1758217036, "type": "Parquet"}, {"name": "dds75-lb-14_raw.ndjson", "size": 155312, "mtime": 1758217036, "type": "NDJSON"}, {"name": "dds75-lb-15.parquet", "size": 6242, "mtime": 1758217042, "type": "Parquet"}, {"name": "dds75-lb-15_raw.ndjson", "size": 167761, "mtime": 1758217042, "type": "NDJSON"}, {"name": "dds75-lb-16.parquet", "size": 6145, "mtime": 1758217048, "type": "Parquet"}, {"name": "dds75-lb-16_raw.ndjson", "size": 150266, "mtime": 1758217048, "type": "NDJSON"}, {"name": "dds75-lb-17.parquet", "size": 6418, "mtime": 1758217054, "type": "Parquet"}, {"name": "dds75-lb-17_raw.ndjson", "size": 182265, "mtime": 1758217054, "type": "NDJSON"}, {"name": "dds75-lb-18.parquet", "size": 6223, "mtime": 1758217060, "type": "Parquet"}, {"name": "dds75-lb-18_raw.ndjson", "size": 157839, "mtime": 1758217060, "type": "NDJSON"}, {"name": "dds75-lb-19.parquet", "size": 6145, "mtime": 1758217066, "type": "Parquet"}, {"name": "dds75-lb-19_raw.ndjson", "size": 153100, "mtime": 1758217066, "type": "NDJSON"}, {"name": "dds75-lb-20.parquet", "size": 5823, "mtime": 1758217072, "type": "Parquet"}, {"name": "dds75-lb-20_raw.ndjson", "size": 106777, "mtime": 1758217072, "type": "NDJSON"}, {"name": "dds75-lb-21.parquet", "size": 5614, "mtime": 1758217078, "type": "Parquet"}, {"name": "dds75-lb-21_raw.ndjson", "size": 103418, "mtime": 1758217078, "type": "NDJSON"}, {"name": "ps-lb-01.parquet", "size": 7857, "mtime": 1758217090, "type": "Parquet"}, {"name": "ps-lb-01_raw.ndjson", "size": 384266, "mtime": 1758217090, "type": "NDJSON"}, {"name": "ps-lb-02.parquet", "size": 8937, "mtime": 1758217101, "type": "Parquet"}, {"name": "ps-lb-02_raw.ndjson", "size": 416435, "mtime": 1758217101, "type": "NDJSON"}, {"name": "ps-lb-03.parquet", "size": 8939, "mtime": 1758217113, "type": "Parquet"}, {"name": "ps-lb-03_raw.ndjson", "size": 404317, "mtime": 1758217113, "type": "NDJSON"}, {"name": "ps-lb-04.parquet", "size": 8902, "mtime": 1758217125, "type": "Parquet"}, {"name": "ps-lb-04_raw.ndjson", "size": 381728, "mtime": 1758217125, "type": "NDJSON"}, {"name": "ps-lb-05.parquet", "size": 9003, "mtime": 1758217137, "type": "Parquet"}, {"name": "ps-lb-05_raw.ndjson", "size": 399404, "mtime": 1758217137, "type": "NDJSON"}, {"name": "ps-lb-06.parquet", "size": 8679, "mtime": 1758217148, "type": "Parquet"}, {"name": "ps-lb-06_raw.ndjson", "size": 385176, "mtime": 1758217148, "type": "NDJSON"}, {"name": "ps-lb-07.parquet", "size": 8888, "mtime": 1758217160, "type": "Parquet"}, {"name": "ps-lb-07_raw.ndjson", "size": 375991, "mtime": 1758217160, "type": "NDJSON"}, {"name": "ps-lb-08.parquet", "size": 8855, "mtime": 1758217172, "type": "Parquet"}, {"name": "ps-lb-08_raw.ndjson", "size": 366017, "mtime": 1758217172, "type": "NDJSON"}, {"name": "ps-lb-09.parquet", "size": 8956, "mtime": 1758217189, "type": "Parquet"}, {"name": "ps-lb-09_raw.ndjson", "size": 386443, "mtime": 1758217189, "type": "NDJSON"}, {"name": "ps-lb-10.parquet", "size": 9111, "mtime": 1758217196, "type": "Parquet"}, {"name": "ps-lb-10_raw.ndjson", "size": 397497, "mtime": 1758217196, "type": "NDJSON"}, {"name": "ps-lb-11.parquet", "size": 8861, "mtime": 1758217213, "type": "Parquet"}, {"name": "ps-lb-11_raw.ndjson", "size": 409256, "mtime": 1758217213, "type": "NDJSON"}, {"name": "ps-lb-12.parquet", "size": 8924, "mtime": 1758217220, "type": "Parquet"}, {"name": "ps-lb-12_raw.ndjson", "size": 390990, "mtime": 1758217220, "type": "NDJSON"}, {"name": "ps-lb-13.parquet", "size": 13996, "mtime": 1758217244, "type": "Parquet"}, {"name": "ps-lb-13_raw.ndjson", "size": 925228, "mtime": 1758217244, "type": "NDJSON"}, {"name": "ps-lb-14.parquet", "size": 8769, "mtime": 1758217256, "type": "Parquet"}, {"name": "ps-lb-14_raw.ndjson", "size": 367657, "mtime": 1758217256, "type": "NDJSON"}, {"name": "ps-lb-15.parquet", "size": 8923, "mtime": 1758217273, "type": "Parquet"}, {"name": "ps-lb-15_raw.ndjson", "size": 391593, "mtime": 1758217273, "type": "NDJSON"}, {"name": "ps-lb-16.parquet", "size": 8952, "mtime": 1758217280, "type": "Parquet"}, {"name": "ps-lb-16_raw.ndjson", "size": 391189, "mtime": 1758217280, "type": "NDJSON"}, {"name": "ps-lb-17.parquet", "size": 13245, "mtime": 1758217303, "type": "Parquet"}, {"name": "ps-lb-17_raw.ndjson", "size": 812705, "mtime": 1758217303, "type": "NDJSON"}, {"name": "ps-lb-18.parquet", "size": 8696, "mtime": 1758217305, "type": "Parquet"}, {"name": "ps-lb-18_raw.ndjson", "size": 278585, "mtime": 1758217305, "type": "NDJSON"}, {"name": "ps-lb-19.parquet", "size": 9229, "mtime": 1758217316, "type": "Parquet"}, {"name": "ps-lb-19_raw.ndjson", "size": 419345, "mtime": 1758217316, "type": "NDJSON"}, {"name": "ps-lb-20.parquet", "size": 11157, "mtime": 1758217328, "type": "Parquet"}, {"name": "ps-lb-20_raw.ndjson", "size": 421054, "mtime": 1758217328, "type": "NDJSON"}, {"name": "ps-lb-21.parquet", "size": 7149, "mtime": 1758217334, "type": "Parquet"}, {"name": "ps-lb-21_raw.ndjson", "size": 191019, "mtime": 1758217334, "type": "NDJSON"}]