[{"name": "burgwald-ps-lb-01.parquet", "size": 6669, "mtime": 1758058699, "type": "Parquet"}, {"name": "burgwald-ps-lb-01_raw.ndjson", "size": 184337, "mtime": 1758058699, "type": "NDJSON"}, {"name": "burgwald-sensecap-01.parquet", "size": 39870, "mtime": 1758058677, "type": "Parquet"}, {"name": "burgwald-sensecap-01_raw.ndjson", "size": 2148599, "mtime": 1758058677, "type": "NDJSON"}, {"name": "dds75-lb-001.parquet", "size": 6262, "mtime": 1758058700, "type": "Parquet"}, {"name": "dds75-lb-001_raw.ndjson", "size": 191871, "mtime": 1758058700, "type": "NDJSON"}, {"name": "dds75-lb-02.parquet", "size": 6436, "mtime": 1758058701, "type": "Parquet"}, {"name": "dds75-lb-02_raw.ndjson", "size": 183148, "mtime": 1758058701, "type": "NDJSON"}, {"name": "dds75-lb-03.parquet", "size": 6246, "mtime": 1758058702, "type": "Parquet"}, {"name": "dds75-lb-03_raw.ndjson", "size": 166261, "mtime": 1758058702, "type": "NDJSON"}, {"name": "dds75-lb-04.parquet", "size": 6321, "mtime": 1758058702, "type": "Parquet"}, {"name": "dds75-lb-04_raw.ndjson", "size": 171696, "mtime": 1758058702, "type": "NDJSON"}, {"name": "dds75-lb-05.parquet", "size": 6359, "mtime": 1758058703, "type": "Parquet"}, {"name": "dds75-lb-05_raw.ndjson", "size": 181024, "mtime": 1758058703, "type": "NDJSON"}, {"name": "dds75-lb-06.parquet", "size": 6222, "mtime": 1758058704, "type": "Parquet"}, {"name": "dds75-lb-06_raw.ndjson", "size": 168182, "mtime": 1758058704, "type": "NDJSON"}, {"name": "dds75-lb-07.parquet", "size": 6387, "mtime": 1758058705, "type": "Parquet"}, {"name": "dds75-lb-07_raw.ndjson", "size": 198425, "mtime": 1758058705, "type": "NDJSON"}, {"name": "dds75-lb-08.parquet", "size": 6346, "mtime": 1758058706, "type": "Parquet"}, {"name": "dds75-lb-08_raw.ndjson", "size": 182119, "mtime": 1758058706, "type": "NDJSON"}, {"name": "dds75-lb-09.parquet", "size": 6368, "mtime": 1758058706, "type": "Parquet"}, {"name": "dds75-lb-09_raw.ndjson", "size": 197111, "mtime": 1758058706, "type": "NDJSON"}, {"name": "dds75-lb-10.parquet", "size": 6365, "mtime": 1758058707, "type": "Parquet"}, {"name": "dds75-lb-10_raw.ndjson", "size": 183645, "mtime": 1758058707, "type": "NDJSON"}, {"name": "dds75-lb-11.parquet", "size": 6352, "mtime": 1758058713, "type": "Parquet"}, {"name": "dds75-lb-11_raw.ndjson", "size": 174615, "mtime": 1758058713, "type": "NDJSON"}, {"name": "dds75-lb-12.parquet", "size": 6349, "mtime": 1758058719, "type": "Parquet"}, {"name": "dds75-lb-12_raw.ndjson", "size": 199734, "mtime": 1758058719, "type": "NDJSON"}, {"name": "dds75-lb-13.parquet", "size": 6246, "mtime": 1758058725, "type": "Parquet"}, {"name": "dds75-lb-13_raw.ndjson", "size": 172529, "mtime": 1758058725, "type": "NDJSON"}, {"name": "dds75-lb-14.parquet", "size": 6453, "mtime": 1758058731, "type": "Parquet"}, {"name": "dds75-lb-14_raw.ndjson", "size": 198890, "mtime": 1758058731, "type": "NDJSON"}, {"name": "dds75-lb-15.parquet", "size": 6311, "mtime": 1758058737, "type": "Parquet"}, {"name": "dds75-lb-15_raw.ndjson", "size": 184889, "mtime": 1758058737, "type": "NDJSON"}, {"name": "dds75-lb-16.parquet", "size": 6305, "mtime": 1758058743, "type": "Parquet"}, {"name": "dds75-lb-16_raw.ndjson", "size": 181477, "mtime": 1758058743, "type": "NDJSON"}, {"name": "dds75-lb-17.parquet", "size": 6862, "mtime": 1758058749, "type": "Parquet"}, {"name": "dds75-lb-17_raw.ndjson", "size": 169411, "mtime": 1758058749, "type": "NDJSON"}, {"name": "dds75-lb-18.parquet", "size": 6463, "mtime": 1758058754, "type": "Parquet"}, {"name": "dds75-lb-18_raw.ndjson", "size": 179005, "mtime": 1758058754, "type": "NDJSON"}, {"name": "dds75-lb-19.parquet", "size": 6267, "mtime": 1758058760, "type": "Parquet"}, {"name": "dds75-lb-19_raw.ndjson", "size": 180419, "mtime": 1758058760, "type": "NDJSON"}]