[{"name": "burgwald-ps-lb-01.parquet", "size": 6659, "mtime": 1757735502, "type": "Parquet"}, {"name": "burgwald-ps-lb-01_raw.ndjson", "size": 199169, "mtime": 1757735502, "type": "NDJSON"}, {"name": "burgwald-sensecap-01.parquet", "size": 39870, "mtime": 1757735486, "type": "Parquet"}, {"name": "burgwald-sensecap-01_raw.ndjson", "size": 2148599, "mtime": 1757735486, "type": "NDJSON"}, {"name": "dds75-lb-001.parquet", "size": 6492, "mtime": 1757735503, "type": "Parquet"}, {"name": "dds75-lb-001_raw.ndjson", "size": 214677, "mtime": 1757735503, "type": "NDJSON"}, {"name": "dds75-lb-02.parquet", "size": 6568, "mtime": 1757735503, "type": "Parquet"}, {"name": "dds75-lb-02_raw.ndjson", "size": 204035, "mtime": 1757735503, "type": "NDJSON"}, {"name": "dds75-lb-03.parquet", "size": 6408, "mtime": 1757735504, "type": "Parquet"}, {"name": "dds75-lb-03_raw.ndjson", "size": 195698, "mtime": 1757735504, "type": "NDJSON"}, {"name": "dds75-lb-04.parquet", "size": 6655, "mtime": 1757735505, "type": "Parquet"}, {"name": "dds75-lb-04_raw.ndjson", "size": 223202, "mtime": 1757735505, "type": "NDJSON"}, {"name": "dds75-lb-05.parquet", "size": 6875, "mtime": 1757735506, "type": "Parquet"}, {"name": "dds75-lb-05_raw.ndjson", "size": 213157, "mtime": 1757735506, "type": "NDJSON"}, {"name": "dds75-lb-06.parquet", "size": 6506, "mtime": 1757735507, "type": "Parquet"}, {"name": "dds75-lb-06_raw.ndjson", "size": 203696, "mtime": 1757735507, "type": "NDJSON"}, {"name": "dds75-lb-07.parquet", "size": 6765, "mtime": 1757735508, "type": "Parquet"}, {"name": "dds75-lb-07_raw.ndjson", "size": 205878, "mtime": 1757735508, "type": "NDJSON"}, {"name": "dds75-lb-08.parquet", "size": 5463, "mtime": 1757735508, "type": "Parquet"}, {"name": "dds75-lb-08_raw.ndjson", "size": 68360, "mtime": 1757735508, "type": "NDJSON"}, {"name": "dds75-lb-09.parquet", "size": 5556, "mtime": 1757735509, "type": "Parquet"}, {"name": "dds75-lb-09_raw.ndjson", "size": 67190, "mtime": 1757735509, "type": "NDJSON"}, {"name": "dds75-lb-10.parquet", "size": 5396, "mtime": 1757735510, "type": "Parquet"}, {"name": "dds75-lb-10_raw.ndjson", "size": 66062, "mtime": 1757735510, "type": "NDJSON"}, {"name": "dds75-lb-11.parquet", "size": 5066, "mtime": 1757735515, "type": "Parquet"}, {"name": "dds75-lb-11_raw.ndjson", "size": 34278, "mtime": 1757735515, "type": "NDJSON"}, {"name": "dds75-lb-12.parquet", "size": 5337, "mtime": 1757735521, "type": "Parquet"}, {"name": "dds75-lb-12_raw.ndjson", "size": 61203, "mtime": 1757735521, "type": "NDJSON"}, {"name": "dds75-lb-13.parquet", "size": 5311, "mtime": 1757735527, "type": "Parquet"}, {"name": "dds75-lb-13_raw.ndjson", "size": 65300, "mtime": 1757735527, "type": "NDJSON"}, {"name": "dds75-lb-14.parquet", "size": 5372, "mtime": 1757735533, "type": "Parquet"}, {"name": "dds75-lb-14_raw.ndjson", "size": 60725, "mtime": 1757735533, "type": "NDJSON"}, {"name": "dds75-lb-15.parquet", "size": 5239, "mtime": 1757735539, "type": "Parquet"}, {"name": "dds75-lb-15_raw.ndjson", "size": 59063, "mtime": 1757735539, "type": "NDJSON"}, {"name": "dds75-lb-16.parquet", "size": 5230, "mtime": 1757735544, "type": "Parquet"}, {"name": "dds75-lb-16_raw.ndjson", "size": 61060, "mtime": 1757735544, "type": "NDJSON"}, {"name": "dds75-lb-17.parquet", "size": 5452, "mtime": 1757735550, "type": "Parquet"}, {"name": "dds75-lb-17_raw.ndjson", "size": 62670, "mtime": 1757735550, "type": "NDJSON"}, {"name": "dds75-lb-18.parquet", "size": 5367, "mtime": 1757735556, "type": "Parquet"}, {"name": "dds75-lb-18_raw.ndjson", "size": 61351, "mtime": 1757735556, "type": "NDJSON"}, {"name": "dds75-lb-19.parquet", "size": 5245, "mtime": 1757735566, "type": "Parquet"}, {"name": "dds75-lb-19_raw.ndjson", "size": 60269, "mtime": 1757735566, "type": "NDJSON"}]